django_cms_tools/__init__.py
django_cms_tools/cms_apps_helper.py
django_cms_tools/cms_plugin_list.py
django_cms_tools/models.py
django_cms_tools/permissions.py
django_cms_tools/version.py
django_cms_tools/dummy_data/__init__.py
django_cms_tools/dummy_data/management/__init__.py
django_cms_tools/dummy_data/management/commands/__init__.py
django_cms_tools/dummy_data/management/commands/create_dummy_pages.py
django_cms_tools/el_pagination_placeholder/__init__.py
django_cms_tools/el_pagination_placeholder/templatetags/__init__.py
django_cms_tools/el_pagination_placeholder/templatetags/el_pagination_placeholder.py
django_cms_tools/filer_tools/__init__.py
django_cms_tools/filer_tools/helper.py
django_cms_tools/filer_tools/management/__init__.py
django_cms_tools/filer_tools/management/commands/__init__.py
django_cms_tools/filer_tools/management/commands/image_info.py
django_cms_tools/filer_tools/management/commands/replace_broken.py
django_cms_tools/fixture_helper/__init__.py
django_cms_tools/fixture_helper/page_utils.py
django_cms_tools/fixture_helper/pages.py
django_cms_tools/management/__init__.py
django_cms_tools/management/commands/__init__.py
django_cms_tools/management/commands/cms_page_info.py
django_cms_tools/management/commands/cms_plugin_info.py
django_cms_tools/management/commands/export_filer_images.py
django_cms_tools/management/commands/generate_add_plugin_test_code.py
django_cms_tools/management/commands/list_page_by_plugin.py
django_cms_tools/management/commands/orphaned_plugin_info.py
django_cms_tools/management/commands/template_info.py
django_cms_tools/plugin_anchor_menu/__init__.py
django_cms_tools/plugin_anchor_menu/app.py
django_cms_tools/plugin_anchor_menu/app_settings.py
django_cms_tools/plugin_anchor_menu/cms_plugins.py
django_cms_tools/plugin_anchor_menu/constants.py
django_cms_tools/plugin_anchor_menu/fixtures.py
django_cms_tools/plugin_anchor_menu/models.py
django_cms_tools-0.7.1.dist-info/LICENSE
django_cms_tools-0.7.1.dist-info/METADATA
django_cms_tools-0.7.1.dist-info/WHEEL
django_cms_tools-0.7.1.dist-info/top_level.txt
django_cms_tools-0.7.1.dist-info/RECORD
