Metadata-Version: 2.1
Name: django-cms-tools
Version: 0.7.1
Summary: Tools/helpers around Django-CMS
Home-page: https://github.com/jedie/django-cms-tools
Author: Jens Diemer
Author-email: django-cms-tools@jensdiemer.de
License: GNU General Public License v3.0 or above
Platform: UNKNOWN
Classifier: Development Status :: 5 - Production/Stable
Classifier: Intended Audience :: Developers
Classifier: License :: OSI Approved :: GNU General Public License v3 or later (GPLv3+)
Classifier: Operating System :: OS Independent
Classifier: Operating System :: MacOS :: MacOS X
Classifier: Operating System :: Microsoft :: Windows
Classifier: Operating System :: POSIX
Classifier: Programming Language :: Python
Classifier: Programming Language :: Python :: 3
Classifier: Programming Language :: Python :: 3.5
Classifier: Programming Language :: Python :: 3.6
Classifier: Programming Language :: Python :: 3 :: Only
Classifier: Programming Language :: Python :: Implementation :: CPython
Classifier: Programming Language :: Python :: Implementation :: PyPy
Classifier: Framework :: Django
Classifier: Framework :: Django :: 1.11
Classifier: Framework :: Django :: 1.8
Classifier: Topic :: Internet
Requires-Python: >=3.5
Requires-Dist: django
Requires-Dist: django-tools (>=0.42.1)
Requires-Dist: django-cms
